chainbench/__init__.py
chainbench/__main__.py
chainbench/main.py
chainbench/profile/__init__.py
chainbench/profile/arbitrum/archive.py
chainbench/profile/arbitrum/general.py
chainbench/profile/avalanche/archive.py
chainbench/profile/avalanche/general.py
chainbench/profile/base/archive.py
chainbench/profile/base/general.py
chainbench/profile/bsc/general.py
chainbench/profile/ethereum/consensus.py
chainbench/profile/ethereum/general.py
chainbench/profile/ethereum/subscriptions.py
chainbench/profile/evm/all.py
chainbench/profile/evm/debug_trace.py
chainbench/profile/evm/get_logs.py
chainbench/profile/evm/heavy.py
chainbench/profile/evm/light.py
chainbench/profile/fantom/archive.py
chainbench/profile/fantom/general.py
chainbench/profile/gnosis/archive.py
chainbench/profile/gnosis/general.py
chainbench/profile/oasis/general.py
chainbench/profile/optimism/archive.py
chainbench/profile/optimism/general.py
chainbench/profile/polygon/general.py
chainbench/profile/ronin/general.py
chainbench/profile/solana/all.py
chainbench/profile/solana/general.py
chainbench/profile/solana/get_program_accounts_shark.py
chainbench/profile/solana/get_program_accounts_stake.py
chainbench/profile/starknet/wallet.py
chainbench/shapes/spike.py
chainbench/shapes/step.py
chainbench/test_data/__init__.py
chainbench/test_data/blockchain.py
chainbench/test_data/ethereum.py
chainbench/test_data/evm.py
chainbench/test_data/solana.py
chainbench/test_data/starknet.py
chainbench/tools/__init__.py
chainbench/tools/discovery/__init__.py
chainbench/tools/discovery/clients.json
chainbench/tools/discovery/methods.json
chainbench/tools/discovery/rpc.py
chainbench/user/__init__.py
chainbench/user/common.py
chainbench/user/http.py
chainbench/user/jsonrpc.py
chainbench/user/protocol/__init__.py
chainbench/user/protocol/ethereum.py
chainbench/user/protocol/evm.py
chainbench/user/protocol/solana.py
chainbench/user/protocol/starknet.py
chainbench/user/tag.py
chainbench/user/wss.py
chainbench/util/__init__.py
chainbench-0.8.8.dist-info/LICENSE
chainbench-0.8.8.dist-info/METADATA
chainbench-0.8.8.dist-info/WHEEL
chainbench-0.8.8.dist-info/entry_points.txt
chainbench-0.8.8.dist-info/RECORD
