Metadata-Version: 2.1
Name: chainbench
Version: 0.8.8
Summary: 
Author: Egor Molodik
Author-email: egor.molodik@chainstack.com
Maintainer: Erwin Wee
Maintainer-email: erwin.wee@chainstack.com
Requires-Python: >=3.10,<4.0
Classifier: Programming Language :: Python :: 3
Classifier: Programming Language :: Python :: 3.10
Classifier: Programming Language :: Python :: 3.11
Requires-Dist: base58 (>=2.1.1,<3.0.0)
Requires-Dist: click (>=8.1.6,<9.0.0)
Requires-Dist: locust (>=2.39.0,<3.0.0)
Requires-Dist: locust-plugins[dashboards] (>=4.5.3,<5.0.0)
Requires-Dist: orjson (>=3.11.2,<4.0.0)
Requires-Dist: solders (>=0.26.0,<0.27.0)
Requires-Dist: tenacity (>=9.0.0,<10.0.0)
Requires-Dist: websocket-client (>=1.8.0,<2.0.0)
Requires-Dist: wsaccel (>=0.6.7,<0.7.0)
